pycounts_pdc_mds/__init__.py
pycounts_pdc_mds/plotting.py
pycounts_pdc_mds/pycounts_pdc_mds.py
pycounts_pdc_mds-0.1.0.dist-info/LICENSE
pycounts_pdc_mds-0.1.0.dist-info/METADATA
pycounts_pdc_mds-0.1.0.dist-info/WHEEL
pycounts_pdc_mds-0.1.0.dist-info/RECORD
