Metadata-Version: 2.1
Name: pycounts_pdc_mds
Version: 0.1.0
Summary: Make a function that counts how many times a word shows up in a given text
License: MIT
Author: Paolo Codina
Requires-Python: >=3.9
Classifier: License :: OSI Approved :: MIT License
Classifier: Programming Language :: Python :: 3
Classifier: Programming Language :: Python :: 3.9
Classifier: Programming Language :: Python :: 3.10
Classifier: Programming Language :: Python :: 3.11
Classifier: Programming Language :: Python :: 3.12
Requires-Dist: matplotlib (>=3.8.2)
